cloudcoil/models/sealed_secrets/__init__.py
cloudcoil/models/sealed_secrets/py.typed
cloudcoil/models/sealed_secrets/v1alpha1.py
cloudcoil_models_sealed_secrets-0.28.0.0.dist-info/METADATA
cloudcoil_models_sealed_secrets-0.28.0.0.dist-info/WHEEL
cloudcoil_models_sealed_secrets-0.28.0.0.dist-info/licenses/LICENSE
cloudcoil_models_sealed_secrets-0.28.0.0.dist-info/RECORD
